{
  "name": "Ltconlinemarkets",
  "address": "0x2516ac5db37df788f8f6ef69ecaa7cd76652eae2",
  "symbol": "LOM",
  "decimals": 18,
  "logo": "https://github.saturndex.org/eth/0x2516ac5db37df788f8f6ef69ecaa7cd76652eae2/logo.png",
  "website": "https://ltconlinemarkets.com",
  "twitter": "https://twitter.com/ltconlinemarke",
  "telegram": "https://t.me/lomofficialsupportglobal",
  "facebook": "https://www.facebook.com/Ltconlinemarkets/",
  "coingecko": "https://www.coingecko.com/en/coins/ltconlinemarkets"
}