{
  "name": "AAVE",
  "address": "0x80fb784b7ed66730e8b1dbd9820afd29931aab03",
  "symbol": "LEND",
  "decimals": 18,
  "logo": "https://github.saturndex.org/eth/0x80fb784b7ed66730e8b1dbd9820afd29931aab03/logo.png",
  "website": "https://aave.com/",
  "twitter": "https://twitter.com/AaveAave",
  "facebook": "https://www.facebook.com/AaveCom/",
  "reddit": "https://www.reddit.com/r/Aave_Official/",
  "coingecko": "https://www.coingecko.com/en/coins/aave/",
  "discord": "https://aave.com/discord",
  "telegram": "https://t.me/Aavesome"
}